olog_tool/__init__.py
olog_tool/__main__.py
olog_tool-0.2.0.dist-info/licenses/LICENSE
olog_tool-0.2.0.dist-info/METADATA
olog_tool-0.2.0.dist-info/WHEEL
olog_tool-0.2.0.dist-info/entry_points.txt
olog_tool-0.2.0.dist-info/top_level.txt
olog_tool-0.2.0.dist-info/RECORD
