Metadata-Version: 2.4
Name: olog-tool
Version: 0.2.0
Summary: A command-line tool for backing up, restoring, and generating reports from Olog servers
Author-email: Andrea Michelotti <andrea.michelotti@lnf.infn.it>
Maintainer-email: Andrea Michelotti <andrea.michelotti@lnf.infn.it>
License-Expression: MIT
Project-URL: Homepage, https://github.com/infn-epics/phoebus-services-tools
Project-URL: Repository, https://github.com/infn-epics/phoebus-services-tools
Project-URL: Issues, https://github.com/infn-epics/phoebus-services-tools/issues
Keywords: olog,backup,restore,reports,phoebus,epics
Classifier: Development Status :: 4 - Beta
Classifier: Intended Audience :: Science/Research
Classifier: Operating System :: OS Independent
Classifier: Programming Language :: Python :: 3
Classifier: Programming Language :: Python :: 3.8
Classifier: Programming Language :: Python :: 3.9
Classifier: Programming Language :: Python :: 3.10
Classifier: Programming Language :: Python :: 3.11
Classifier: Programming Language :: Python :: 3.12
Classifier: Topic :: Scientific/Engineering
Classifier: Topic :: Utilities
Requires-Python: >=3.8
License-File: LICENSE
Requires-Dist: requests>=2.31.0
Requires-Dist: reportlab>=4.0.0
Dynamic: license-file
